MIDI/__init__.py
MIDI/base.py
MIDI/partitioner.py
MIDI/Events/__init__.py
MIDI/Events/event.py
MIDI/Events/meta.py
MIDI/Events/midi.py
MIDI/Events/sysex.py
MIDI/Events/messages/__init__.py
MIDI/Events/messages/controls.py
MIDI/Events/messages/converters.py
MIDI/Events/messages/exclusive.py
MIDI/Events/messages/notes.py
MIDI/Events/messages/other.py
MIDI/chunks/__init__.py
MIDI/chunks/chunk.py
MIDI/chunks/header.py
MIDI/chunks/track.py
MIDI/util/__init__.py
MIDI/util/enums.py
usr/local/bin/parse_midi
MIDIFile-0.1.0.dist-info/LICENSE.txt
MIDIFile-0.1.0.dist-info/METADATA
MIDIFile-0.1.0.dist-info/WHEEL
MIDIFile-0.1.0.dist-info/top_level.txt
MIDIFile-0.1.0.dist-info/RECORD
