Metadata-Version: 2.1
Name: MIDIFile
Version: 0.1.0
Summary: A simple MIDI File parser
Home-page: UNKNOWN
Author: Julian Porter
Author-email: julian@porternet.org
License: UNKNOWN
Keywords: MIDI
Platform: UNKNOWN
Classifier: Development Status :: 4 - Beta
Classifier: Environment :: Console
Classifier: Intended Audience :: Developers
Classifier: Intended Audience :: Other Audience
Classifier: License :: OSI Approved :: MIT License
Classifier: Natural Language :: English
Classifier: Operating System :: MacOS
Classifier: Operating System :: POSIX :: Linux
Classifier: Programming Language :: Python :: 3
Classifier: Programming Language :: Python :: 3.6
Classifier: Programming Language :: Python :: 3.7
Classifier: Programming Language :: Python :: 3.8
Classifier: Topic :: Multimedia :: Sound/Audio :: MIDI
Requires-Python: >=3.6, <4
